LICENSE
README.md
pyproject.toml
setup.cfg
setup.py
lpsmods_api/__init__.py
lpsmods_api/models.py
lpsmods_api/py.typed
lpsmods_api.egg-info/PKG-INFO
lpsmods_api.egg-info/SOURCES.txt
lpsmods_api.egg-info/dependency_links.txt
lpsmods_api.egg-info/not-zip-safe
lpsmods_api.egg-info/requires.txt
lpsmods_api.egg-info/top_level.txt