Metadata-Version: 2.1
Name: lpsmods-api
Version: 0.0.1
Summary: Template python package.
Home-page: https://github.com/legopitstop/lpsmods_api/
Author: Legopitstop
Author-email: contact@lpsmods.dev
License: MIT
Project-URL: Download, https://github.com/legopitstop/lpsmods-api/releases
Project-URL: Documentation, https://docs.lpsmods.dev/lpsmods-api/
Project-URL: Source Code, https://github.com/legopitstop/lpsmods-api
Keywords: lpsmods,lpsmods-api,lpsmods_api,api,python
Classifier: Development Status :: 4 - Beta
Classifier: Intended Audience :: Developers
Classifier: License :: OSI Approved :: MIT License
Classifier: Programming Language :: Python :: 3.12
Requires-Python: >=3.6
Provides-Extra: testing
License-File: LICENSE
